gemeaux/__init__.py
gemeaux/exceptions.py
gemeaux/handlers.py
gemeaux/responses.py
gemeaux-0.0.3.dist-info/METADATA
gemeaux-0.0.3.dist-info/WHEEL
gemeaux-0.0.3.dist-info/licenses/LICENSE
gemeaux-0.0.3.dist-info/RECORD
