Metadata-Version: 2.4
Name: gemeaux
Version: 0.0.3
Summary: A Python Gemini server
Project-URL: homepage, https://github.com/brunobord/gemeaux
Author-email: Bruno Bord <bruno@jehaisleprintemps.net>
License-Expression: MIT
License-File: LICENSE
Keywords: gemini,protocol,server
Classifier: Development Status :: 3 - Alpha
Classifier: Intended Audience :: Developers
Classifier: License :: OSI Approved :: MIT License
Classifier: Operating System :: OS Independent
Classifier: Programming Language :: Python
Classifier: Programming Language :: Python :: 3
Classifier: Programming Language :: Python :: 3.9
Classifier: Programming Language :: Python :: 3.10
Classifier: Programming Language :: Python :: 3.11
Classifier: Programming Language :: Python :: 3.12
Classifier: Programming Language :: Python :: 3.13
Requires-Python: >=3.9
